Workbook

Sheet Chart of Accounts
A1: Chart of Accounts and Opening Balances as at 31 March
A2: Account No. | B2: Account Name | C2: Balance
C3: DR | D3: CR
A4: 101 | B4: Cash at Bank - ANZ | C4: =12580+2290 -> 14870
A5: 110 | B5: Accounts Receivable | C5: =+C41 -> 56518
A6: 112 | B6: Inventory | C6: =+E59 -> 24480
A7: 115 | B7: Prepaid Insurance | C7: -
A8: 116 | B8: Prepaid Rent | C8: 15000
A9: 118 | B9: Office Supplies | C9: 1520
A10: 130 | B10: Store Equipment | C10: 29080
A11: 131 | B11: Accumulated Depreciation - Store Equipment | D11: 14040
A12: 135 | B12: Computer Equipment | C12: 24460
A13: 136 | B13: Accumulated Depreciation - Computer Equipment | D13: 15288
A14: 200 | B14: GST Clearing (Tax Payable GST) | D14: 12450
A15: 201 | B15: Accounts Payable | D15: 28970
A16: 203 | B16: Wages Payable | D16: -
A17: 205 | B17: PAYG Tax Payable | D17: 5180
A18: 301 | B18: Capital | D18: 90000
A19: 302 | B19: Drawings
A20: 307 | B20: Profit or Loss Summary
A21: 401 | B21: Sales Revenue
A22: 402 | B22: Sales Returns & Allowances
A23: 501 | B23: Cost of Sales
A24: 503 | B24: Bank Charges
A25: 505 | B25: Depreciation Expense - Computer Equipment
A26: 506 | B26: Depreciation Expense - Store Equipment
A27: 510 | B27: Electrical Repairs Expense
A28: 520 | B28: Insurance Expense
A29: 542 | B29: Office Supplies Expense
A30: 560 | B30: Rent Expense
... A33: 585 | B33: Wages Expense
C34: =SUM(C4:C33) -> 165928 | D34: =SUM(D4:D33) -> 165928
A36: Accounts Receivable Subsidiary Ledger
A37: as at 31 March
B38: Creative Industries | C38: 23120
B39: Kelvin Grove High School | C39: 7448
B40: The Gap High School | C40: 25950
C41: =SUM(C38:C40) -> 56518
A43: Accounts Payable Subsidiary Ledger
A44: as at 31 March
B46: Able Accountants | D46: 3850
B47: Fender Guitars | D47: 16500
B48: Insight Computers | D48: 4520
B49: Yamaha | D49: 4100
D50: =SUM(D46:D49) -> 28970
A52: List of Inventory Items
A53: as at 31 March | D53: Unit Cost $ | E53: Total Value $ | F53: Unit Selling Price $
C54: Number of units | D54: (excl GST) | E54: (excl GST) | F54: (excl GST)
B55: Acoustic Guitar | C55: 64 | D55: 180 | E55: =+C55*D55 -> 11520 | F55: =+D55*2 -> 360
B56: Bass Guitar | C56: 23 | D56: 170 | E56: =+C56*D56 -> 3910 | F56: =+D56*2 -> 340
B57: Electric Guitar | C57: 20 | D57: 190 | E57: =+C57*D57 -> 3800 | F57: =+D57*2 -> 380
B58: Student Pack | C58: 35 | D58: 150 | E58: =+C58*D58 -> 5250 | F58: =+D58*2 -> 300
E59: =SUM(E55:E58) -> 24480

Sheet Journals
A1: SALES JOURNAL (SJ18) | C1: Page 18
A2: Date | B2: Account Debited | C2: Invoice No. | D2: Post Ref | E2: Accounts Receivable DR | F2: GST Clearing CR | G2: Sales Revenue CR | H2: Cost of Sales Dr Inventory Cr
A3: 44287 | B3: Creative Industries | C3: GG32 | D3: ü | E3: =SUM(F3:G3) -> 11880 | F3: =G3*0.1 -> 1080 | G3: =30*'Chart of Accounts'!F55 -> 10800 | H3: =30*'Chart of Accounts'!D55 -> 5400
A4: 44295 | B4: Kelvin Grove High School | C4: GG33 | D4: ü | E4: =G4+F4 -> 12144 | F4: =G4*0.1 -> 1104 | G4: =6*'Chart of Accounts'!F56+30*'Chart of Accounts'!F58 -> 11040 | H4: =6*'Chart of Accounts'!D56+30*'Chart of Accounts'!D58 -> 5520
A5: 44311 | B5: The Gap High School | C5: GG34 | D5: ü | E5: =G5+F5 -> 14520 | F5: =G5*0.1 -> 1320 | G5: =20*'Chart of Accounts'!F58+20*'Chart of Accounts'!F55 -> 13200 | H5: =20*'Chart of Accounts'!D58+20*'Chart of Accounts'!D55 -> 6600
E8: =SUM(E3:E5) -> 38544 | F8: =SUM(F3:F5) -> 3504 | G8: =SUM(G3:G5) -> 35040 | H8: =SUM(H3:H5) -> 17520
A9: Posting References for Totals | E9: 110 | F9: 200 | G9: 401 | H9: 501/112
G10: Proof | H10: =SUM(E8)-SUM(F8:G8) -> 0
B11: PURCHASES JOURNAL (PJ18) | C11: Page 18
A12: Date | B12: Account Credited | D12: Post Ref | E12: Inventory DR | F12: GST Clearing DR | G12: Accounts Payable CR
A13: 44288 | B13: Yamaha | D13: ü | E13: =40*'Chart of Accounts'!D55 -> 7200 | F13: =E13*0.1 -> 720 | G13: =SUM(E13:F13) -> 7920
A14: 44296 | B14: Fender Guitars | D14: ü | E14: =20*'Chart of Accounts'!D58 -> 3000 | F14: =E14*0.1 -> 300 | G14: =E14+F14 -> 3300
E17: =SUM(E13:E14) -> 10200 | F17: =SUM(F13:F14) -> 1020 | G17: =SUM(G13:G14) -> 11220
A18: Posting References for Totals | E18: 112 | F18: 200 | G18: 201
F19: Proof | G19: =SUM(G17)-SUM(E17:F17) -> 0
A21: CASH RECEIPTS JOURNAL (CRJ17) | C21: Page 17
A22: Date | B22: Account Credited | C22: Post Ref | D22: Cash at Bank Dr | E22: Sales Revenue Cr | F22: Accounts Receivable Cr | G22: Other Accounts Cr | H22: GST Clearing Cr | I22: Cost of Sales Dr Inventory Cr
A23: 44289 | C23: C324 | D23: =E23+H23 -> 1672 | E23: =4*'Chart of Accounts'!F57 -> 1520 | H23: =E23*0.1 -> 152 | I23: =4*'Chart of Accounts'!D57 -> 760
A24: 44307 | B24: Creative Industries | C24: ü | D24: 15200 | F24: =D24 -> 15200
A25: 44313 | B25: Kelvin Grove High School | C25: ü | D25: 6000 | F25: =D25 -> 6000
A26: 44313 | C26: C325 | D26: =E26+H26 -> 2244 | E26: =6*'Chart of Accounts'!F56 -> 2040 | H26: =E26*0.1 -> 204 | I26: =6*'Chart of Accounts'!D56 -> 1020
A27: 44315 | B27: The Gap High School | C27: ü | D27: 22000 | F27: =D27 -> 22000
A28: 44315 | B28: Capital | C28: 301 | D28: 2500 | G28: =D28 -> 2500
D30: =SUM(D23:D28) -> 49616 | E30: =SUM(E23:E28) -> 3560 | F30: =SUM(F23:F28) -> 43200 | G30: =SUM(G23:G28) -> 2500 | H30: =SUM(H23:H28) -> 356 | I30: =SUM(I23:I28) -> 1780
A31: Posting References for Totals | D31: 101 | E31: 401 | F31: 110 | G31: x | H31: 200 | I31: 501/112
G32: Proof | H32: =SUM(D30)-SUM(E30:H30) -> 0
A34: CASH PAYMENTS JOURNAL (CPJ25) | C34: Page 25
A36: Date | B36: Account Debited | C36: Chq. No. | D36: Post Ref | E36: Accounts Payable Dr | F36: Other Accounts Dr | G36: GST Clearing Dr | H36: Cash at Bank Cr
A37: 44286 | B37: Electrical Repairs Expense | C37: 46 | D37: 510 | F37: =H37-G37 -> 300 | G37: =H37/11 -> 30 | H37: 330
A38: 44287 | B38: Office Supplies | C38: 47 | D38: 118 | F38: =H38-G38 -> 700 | G38: =H38/11 -> 70 | H38: 770
A39: 44289 | B39: Prepaid Insurance | C39: 48 | D39: 115 | F39: =H39-G39 -> 1200 | G39: =H39/11 -> 120 | H39: 1320
A40: 44289 | B40: Drawings | C40: 49 | D40: 302 | F40: 1000 | H40: 1000
A41: 44289 | B41: Wages Expense | C41: 50 | D41: 585 | F41: 3400 | H41: 3400
A42: 44299 | B42: Able Accountants | C42: 51 | D42: ü | E42: 3850 | H42: 3850
A43: 44306 | B43: Fender Guitars | C43: 52 | D43: ü | E43: 15400 | H43: 15400
A44: 44311 | B44: Telephone and Internet Expense | C44: 53 | D44: 580 | F44: =H44-G44 -> 250 | G44: =H44/11 -> 25 | H44: 275
A45: 44315 | B45: GST Clearing (Tax Payable GST) | C45: 54 | D45: 200 | F45: 12450 | H45: 12450
A46: 44315 | B46: PAYG Tax Payable | C46: 54 | D46: 203 | F46: 5180 | H46: 5180
A47: 44315 | B47: Utilities Expense | C47: 55 | D47: 582 | F47: =H47-G47 -> 260 | G47: =H47/11 -> 26 | H47: 286
A48: 44315 | B48: Electrical Repairs Expense | C48: 56 | D48: 510 | F48: =H48-G48 -> 130 | G48: =H48/11 -> 13 | H48: 143
A49: 44315 | B49: Bank Charges | F49: 25 | H49: 25
E51: =SUM(E37:E49) -> 19250 | F51: =SUM(F37:F49) -> 24895 | G51: =SUM(G37:G49) -> 284 | H51: =SUM(H37:H49) -> 44429
A52: Posting References for Totals | E52: 201 | F52: x | G52: 200 | H52: 101
G53: Proof | H53: =SUM(H51)-SUM(E51:G51) -> 0
A54: General Journal (GJ62) | C54: Page 62
A57: Date | B57: Account Details | C57: Post Ref | D57: Debit | E57: Credit
A58: 44286 | B58: Computer Equipment | C58: 135 | D58: =E60-D59 -> 1220
B59: GST Clearing (Tax Payable GST) | C59: 200 | D59: =E60/11 -> 122
B60: Accounts Payable-Insight Computers | C60: 201/ü | E60: 1342
A62: 44306 | B62: Sales Returns & Allowances | C62: 402 | D62: =2*'Chart of Accounts'!F58 -> 600
B63: GST Clearing (Tax Payable GST) | C63: 200 | D63: =D62*0.1 -> 60
B64: Accounts Receivable-Kelvin Grove High School | C64: 110/ü | E64: =D62+D63 -> 660
A66: 44306 | B66: Inventory | C66: 112 | D66: =2*'Chart of Accounts'!D58 -> 300
B67: Cost of Sales | E67: =D66 -> 300
A69: 44313 | B69: Accounts Payable-Yamaha | C69: 201/ü | D69: =E70+E71 -> 396
B70: GST Clearing (Tax Payable GST) | C70: 200 | E70: =E71*0.1 -> 36
B71: Inventory | C71: 112 | E71: =2*'Chart of Accounts'!D55 -> 360
A73: 44315 | B73: Wages Expense | C73: 585 | D73: 1020
B74: PAYG Tax Payable | E74: =D73 -> 1020
A79: General Journal (GJ63) | C79: Page 63
B80: Adjusting Entries
A81: 44315 | B81: Wages Expense | C81: 585 | D81: 600
B82: Wages Payable | C82: 203 | E82: =D81 -> 600
A84: 44315 | B84: Insurance Expense | C84: 520 | D84: 100
B85: Prepaid Insurance | C85: 115 | E85: 100
A87: 44315 | B87: Depreciation Expense - Store Equipment | C87: 506 | D87: 468
B88: Accumulated Depreciation - Store Equipment | C88: 131 | E88: 468
A90: 44315 | B90: Depreciation Expense - Computer Equipment | C90: 505 | D90: 570
B91: Accumulated Depreciation - Computer Equipment | C91: 136 | E91: =D90 -> 570
A93: 44315 | B93: Office Supplies Expense | C93: 542 | D93: 1850
B94: Office Supplies | C94: 118 | E94: =D93 -> 1850
A96: 44315 | B96: Rent Expense | C96: 560 | D96: 5000
B97: Prepaid Rent | C97: 116 | E97: =D96 -> 5000
A107: General Journal (GJ64) | C107: Page 64
B108: Closing Entries
A109: 44315 | B109: Sales Revenue | C109: 401 | D109: 38600
B110: Profit or Loss Summary | C110: 307 | E110: 38600
A112: 44315 | B112: Profit or Loss Summary | C112: 307 | D112: 600
B113: Sales Returns & Allowances | C113: 402 | E113: 600
A115: 44315 | B115: Profit or Loss Summary | C115: 307 | D115: =SUM(E116:E126) -> 32973
B116: Cost of Sales | C116: 501 | E116: 19000
B117: Bank Charges | C117: 503 | E117: 25
B118: Depreciation - Computer Equipment | C118: 505 | E118: 570
B119: Depreciation - Store Equipment | C119: 506 | E119: 468
B120: Electrical Repairs Expense | C120: 510 | E120: 430
B121: Insurance Expense | C121: 520 | E121: 100
B122: Office Supplies Expense | C122: 542 | E122: 1850
B123: Rent Expense | C123: 560 | E123: 5000
B124: Telephone and Internet Expense | C124: 580 | E124: 250
B125: Utilities Expense | C125: 582 | E125: 260
B126: Wages Expense | C126: 585 | E126: 5020
A128: 44315 | B128: Profit or Loss Summary | C128: 307 | D128: 5027
B129: Capital | C129: 301 | E129: 5027
A131: 44315 | B131: Capital | C131: 301 | D131: 1000
B132: Drawings | C132: 302 | E132: 1000

Sheet Subsid Ledgers
A1: Accounts Receivable Subsidiary Ledger
A3: Account: | B3: =+'Chart of Accounts'!B38 -> Creative Industries
C4: Jnl Ref | D4: Debit | E4: Credit | F4: Balance
A5: Date | F5: Debit | G5: Credit
A6: 43555 | B6: Bal | F6: =+'Chart of Accounts'!C38 -> 23120
A7: 44287 | C7: SJ18 | D7: =Journals!E3 -> 11880 | F7: =IF(A7="","",F6+D7-E7) -> 35000
A8: 44307 | C8: CRJ17 | E8: =Journals!F24 -> 15200 | F8: =IF(A8="","",F7+D8-E8) -> 19800
A10: Account: | B10: =+'Chart of Accounts'!B39 -> Kelvin Grove High School
C11: Jnl Ref | D11: Debit | E11: Credit | F11: Balance
A12: Date | F12: Debit | G12: Credit
A13: =+A6 -> 43555 | B13: Bal | F13: =+'Chart of Accounts'!C39 -> 7448
A14: 44295 | C14: SJ18 | D14: =Journals!E4 -> 12144 | F14: =IF(A14="","",F13+D14-E14) -> 19592
A15: 44306 | C15: GJ62 | E15: =Journals!E64 -> 660 | F15: =IF(A15="","",F14+D15-E15) -> 18932
A16: 44313 | C16: CRJ17 | E16: =Journals!F25 -> 6000 | F16: =IF(A16="","",F15+D16-E16) -> 12932
A18: Account: | B18: =+'Chart of Accounts'!B40 -> The Gap High School
C19: Jnl Ref | D19: Debit | E19: Credit | F19: Balance
A20: Date | F20: Debit | G20: Credit
A21: =+A6 -> 43555 | B21: Bal | F21: =+'Chart of Accounts'!C40 -> 25950
A22: 44311 | C22: SJ18 | D22: =Journals!E5 -> 14520 | F22: =IF(A22="","",F21+D22-E22) -> 40470
A23: 44315 | C23: CPJ17 | E23: =Journals!F27 -> 22000 | F23: =IF(A23="","",F22+D23-E23) -> 18470
A25: SCHEDULE OF ACCOUNTS RECEIVABLE AS AT 30 APRIL
B27: =+B3 -> Creative Industries | F27: =+F8 -> 19800
B28: =+B10 -> Kelvin Grove High School | F28: =+F16 -> 12932
B29: =+B18 -> The Gap High School | F29: =+F23 -> 18470
F30: =SUM(F27:F29) -> 51202
A31: Confirm Subsidiary Ledger Matches General Ledger Control Account | F31: Y/N | G31: YES
A33: Accounts Payable Subsidiary Ledger
A35: Account: | B35: =+'Chart of Accounts'!B46 -> Able Accountants
C36: Jnl Ref | D36: Debit | E36: Credit | F36: Balance
A37: Date | F37: Debit | G37: Credit
A38: =+A6 -> 43555 | B38: Bal | G38: =+'Chart of Accounts'!D46 -> 3850
A39: 44299 | C39: CPJ25 | D39: =Journals!E42 -> 3850 | G39: =IF(A39="","",G38+E39-D39) -> 0
A41: Account: | B41: =+'Chart of Accounts'!B47 -> Fender Guitars
C42: Jnl Ref | D42: Debit | E42: Credit | F42: Balance
A43: Date | F43: Debit | G43: Credit
A44: =+A6 -> 43555 | B44: Bal | G44: =+'Chart of Accounts'!D47 -> 16500
A45: 44296 | C45: PJ18 | E45: =Journals!G14 -> 3300 | G45: =IF(A45="","",G44+E45-D45) -> 19800
A46: 44306 | C46: CPJ25 | D46: =Journals!E43 -> 15400 | G46: =IF(A46="","",G45+E46-D46) -> 4400
A48: Account: | B48: =+'Chart of Accounts'!B48 -> Insight Computers
C49: Jnl Ref | D49: Debit | E49: Credit | F49: Balance
A50: Date | F50: Debit | G50: Credit
A51: =+A6 -> 43555 | B51: Bal | G51: =+'Chart of Accounts'!D48 -> 4520
A52: 44286 | C52: GJ62 | E52: =Journals!E60 -> 1342 | G52: =IF(A52="","",G51+E52-D52) -> 5862
A54: Account: | B54: =+'Chart of Accounts'!B49 -> Yamaha
C55: Jnl Ref | D55: Debit | E55: Credit | F55: Balance
A56: Date | F56: Debit | G56: Credit
A57: =+A6 -> 43555 | B57: Bal | G57: =+'Chart of Accounts'!D49 -> 4100
A58: 44288 | C58: PJ18 | E58: =Journals!G13 -> 7920 | G58: =IF(A58="","",G57+E58-D58) -> 12020
A59: 44313 | C59: GJ62 | D59: =Journals!D69 -> 396 | G59: =IF(A59="","",G58+E59-D59) -> 11624
A61: SCHEDULE OF ACCOUNTS PAYABLE AS AT 30 APRIL
B63: =+B35 -> Able Accountants | G63: =+G39 -> 0
B64: =+B41 -> Fender Guitars | G64: =+G46 -> 4400
B65: =+B48 -> Insight Computers | G65: =+G52 -> 5862
B66: =+B54 -> Yamaha | G66: =+G59 -> 11624
G67: =SUM(G63:G66) -> 21886
A68: Confirm Subsidiary Ledger Matches General Ledger Control Account | G68: Y/N | H68: YES

Sheet Gen Ledger
A1: Account: | B1: Cash at Bank | E1: Account No. | F1: 101
C3: Jnl Ref | D3: Debit | E3: Credit | F3: Balance
A4: Date | F4: Debit | G4: Credit
A5: 43555 | F5: =+'Chart of Accounts'!C4 -> 14870
A6: 44315 | C6: CRJ17 | D6: =Journals!D30 -> 49616 | F6: =IF(A6="","",F5+D6-E6) -> 64486
A7: 44315 | C7: CPJ25 | E7: =Journals!H51 -> 44429 | F7: =IF(A7="","",F6+D7-E7) -> 20057
A9: Account: | B9: Accounts Receivable | E9: Account No. | F9: 110
C11: Jnl Ref | D11: Debit | E11: Credit | F11: Balance
A12: Date | F12: Debit | G12: Credit
A13: =+A5 -> 43555 | F13: =+'Chart of Accounts'!C5 -> 56518
A14: 44306 | C14: GJ62 | E14: =Journals!E64 -> 660 | F14: =IF(A14="","",F13+D14-E14) -> 55858
A15: 44315 | C15: SJ18 | D15: =Journals!E8 -> 38544 | F15: =IF(A15="","",F14+D15-E15) -> 94402
A16: 44315 | C16: CRJ17 | E16: =Journals!F30 -> 43200 | F16: =IF(A16="","",F15+D16-E16) -> 51202
A18: Account: | B18: Inventory | E18: Account No. | F18: 112
C20: Jnl Ref | D20: Debit | E20: Credit | F20: Balance
A21: Date | F21: Debit | G21: Credit
A22: =+A5 -> 43555 | F22: =+'Chart of Accounts'!C6 -> 24480
A23: 44306 | C23: GJ62 | D23: =Journals!D66 -> 300 | F23: =IF(A23="","",F22+D23-E23) -> 24780
A24: 44313 | C24: GJ62 | E24: =Journals!E71 -> 360 | F24: =IF(A24="","",F23+D24-E24) -> 24420
A25: 44315 | C25: SJ18 | E25: =Journals!H8 -> 17520 | F25: =IF(A25="","",F24+D25-E25) -> 6900
A26: 44315 | C26: PJ18 | D26: =Journals!E17 -> 10200 | F26: =IF(A26="","",F25+D26-E26) -> 17100
A27: 44315 | C27: CRJ17 | E27: =Journals!I30 -> 1780 | F27: =IF(A27="","",F26+D27-E27) -> 15320
A30: Account: | B30: Prepaid Insurance | E30: Account No. | F30: 115
C32: Jnl Ref | D32: Debit | E32: Credit | F32: Balance
A33: Date | F33: Debit | G33: Credit
A34: 44289 | C34: CPJ25 | D34: =Journals!F39 -> 1200 | F34: =D34 -> 1200
A35: 44315 | C35: GJ63 | E35: =Journals!E85 -> 100 | F35: =IF(A35="","",F34+D35-E35) -> 1100
A37: Account: | B37: Prepaid Rent | E37: Account No. | F37: 116
C39: Jnl Ref | D39: Debit | E39: Credit | F39: Balance
A40: Date | F40: Debit | G40: Credit
A41: =+A5 -> 43555 | F41: =+'Chart of Accounts'!C8 -> 15000
A42: 44315 | C42: GJ63 | E42: =Journals!E97 -> 5000 | F42: =IF(A42="","",F41+D42-E42) -> 10000
A44: Account: | B44: Office Supplies | E44: Account No. | F44: 118
C46: Jnl Ref | D46: Debit | E46: Credit | F46: Balance
A47: Date | F47: Debit | G47: Credit
A48: =+A5 -> 43555 | F48: 1520
A49: 44287 | C49: CPJ25 | D49: =Journals!F38 -> 700 | F49: =IF(A49="","",F48+D49-E49) -> 2220
A50: 44315 | C50: GJ63 | E50: =Journals!E94 -> 1850 | F50: =IF(A50="","",F49+D50-E50) -> 370
A52: Account: | B52: Store Equipment | E52: Account No. | F52: 130
C54: Jnl Ref | D54: Debit | E54: Credit | F54: Balance
A55: Date | F55: Debit | G55: Credit
A56: =+A5 -> 43555 | F56: =+'Chart of Accounts'!C10 -> 29080
A58: Account: | B58: Accumulated Depreciation - Store Equipment | E58: Account No. | F58: 131
C60: Jnl Ref | D60: Debit | E60: Credit | F60: Balance
A61: Date | F61: Debit | G61: Credit
A62: =+A5 -> 43555 | G62: =+'Chart of Accounts'!D11 -> 14040
A63: 44315 | C63: GJ63 | E63: =Journals!E88 -> 468 | G63: =IF(A63="","",G62+E63-D63) -> 14508
A65: Account: | B65: Computer Equipment | E65: Account No. | F65: 135
C67: Jnl Ref | D67: Debit | E67: Credit | F67: Balance
A68: Date | F68: Debit | G68: Credit
A69: =+A5 -> 43555 | F69: =+'Chart of Accounts'!C12 -> 24460
A70: 44286 | C70: GJ62 | D70: =Journals!D58 -> 1220 | F70: =IF(A70="","",F69+D70-E70) -> 25680
A72: Account: | B72: Accumulated Depreciation - Computer Equipment | E72: Account No. | F72: 136
C74: Jnl Ref | D74: Debit | E74: Credit | F74: Balance
A75: Date | F75: Debit | G75: Credit
A76: =+A5 -> 43555 | G76: =+'Chart of Accounts'!D13 -> 15288
A77: 44315 | C77: GJ63 | E77: =Journals!E91 -> 570 | G77: =IF(A77="","",G76+E77-D77) -> 15858
A80: Account: | B80: GST Clearing (Tax Payable GST) | E80: Account No. | F80: 200
C82: Jnl Ref | D82: Debit | E82: Credit | F82: Balance
A83: Date | F83: Debit | G83: Credit
A84: =+A5 -> 43555 | G84: =+'Chart of Accounts'!D14 -> 12450
A85: 44286 | C85: GJ62 | D85: =Journals!D59 -> 122 | G85: =IF(A85="","",G84+E85-D85) -> 12328
A86: 44306 | C86: GJ62 | D86: =Journals!D63 -> 60 | G86: =IF(A86="","",G85+E86-D86) -> 12268
A87: 44313 | C87: GJ62 | E87: =Journals!E70 -> 36 | G87: =IF(A87="","",G86+E87-D87) -> 12304
A88: 44315 | C88: CPJ25 | D88: =Journals!F45 -> 12450 | G88: =IF(A88="","",G87+E88-D88) -> -146
A89: 44315 | C89: SJ18 | E89: =Journals!F8 -> 3504 | G89: =IF(A89="","",G88+E89-D89) -> 3358
A90: 44315 | C90: PJ18 | D90: =Journals!F17 -> 1020 | G90: =IF(A90="","",G89+E90-D90) -> 2338
A91: 44315 | C91: CRJ17 | E91: =Journals!H30 -> 356 | G91: =IF(A91="","",G90+E91-D91) -> 2694
A92: 44315 | C92: CPJ25 | D92: =Journals!G51 -> 284 | G92: =G91-D92 -> 2410
A93: Account: | B93: Accounts Payable | E93: Account No. | F93: 201
C95: Jnl Ref | D95: Debit | E95: Credit | F95: Balance
A96: Date | F96: Debit | G96: Credit
A97: =+A5 -> 43555 | G97: =+'Chart of Accounts'!D15 -> 28970
A98: 44286 | C98: GJ62 | E98: =Journals!E60 -> 1342 | G98: =IF(A98="","",G97+E98-D98) -> 30312
A99: 44313 | C99: GJ62 | D99: =Journals!D69 -> 396 | G99: =IF(A99="","",G98+E99-D99) -> 29916
A100: 44315 | C100: PJ18 | E100: =Journals!G17 -> 11220 | G100: =IF(A100="","",G99+E100-D100) -> 41136
A101: 44315 | C101: CPJ25 | D101: =Journals!E51 -> 19250 | G101: =IF(A101="","",G100+E101-D101) -> 21886
A103: Account: | B103: Wages Payable | E103: Account No. | F103: 203
C105: Jnl Ref | D105: Debit | E105: Credit | F105: Balance
A106: Date | F106: Debit | G106: Credit
A107: 44315 | C107: GJ63 | E107: =Journals!E82 -> 600 | G107: =E107 -> 600
A109: Account: | B109: PAYG Tax Payable | E109: Account No. | F109: 205
C111: Jnl Ref | D111: Debit | E111: Credit | F111: Balance
A112: Date | F112: Debit | G112: Credit
A113: =+A5 -> 43555 | G113: =+'Chart of Accounts'!D17 -> 5180
A114: 44315 | C114: CPJ25 | D114: =Journals!F46 -> 5180 | G114: =IF(A114="","",G113+E114-D114) -> 0
A115: 44315 | C115: CJ62 | E115: =Journals!E74 -> 1020 | G115: =IF(A115="","",G114+E115-D115) -> 1020
A117: Account: | B117: Capital | E117: Account No. | F117: 301
C120: Jnl Ref | D120: Debit | E120: Credit | F120: Balance
A121: Date | F121: Debit | G121: Credit
A122: =+A5 -> 43555 | G122: =+'Chart of Accounts'!D18 -> 90000
A123: 44315 | C123: CRJ17 | E123: =Journals!G30 -> 2500 | G123: =IF(A123="","",G122+E123-D123) -> 92500
A124: 44315 | C124: GJ64 | E124: =Journals!E129 -> 5027 | G124: =IF(A124="","",G123+E124-D124) -> 97527
A125: 44315 | C125: GJ64 | D125: =Journals!D131 -> 1000 | G125: =IF(A125="","",G124+E125-D125) -> 96527
A127: Account: | B127: Drawings | E127: Account No. | F127: 302
C129: Jnl Ref | D129: Debit | E129: Credit | F129: Balance
A130: Date | F130: Debit | G130: Credit
A131: 44289 | C131: CPJ25 | D131: =Journals!F40 -> 1000 | F131: =D131 -> 1000
A132: 44315 | C132: GJ64 | E132: =Journals!E132 -> 1000 | F132: =F131-E132 -> 0
A134: Account: | B134: Profit or Loss Summary | E134: Account No. | F134: 307
...

Sheet Worksheet
A1: Worksheet for month ended 30 April
B4: Account Title | C4: Unadjusted Trial Balance | E4: Adjustments | I4: Adjusted Trial Balance | K4: Income Statement | M4: Balance Sheet
C5: DR | D5: CR | E5: Letter of adj | F5: DR | G5: Letter of adj | H5: CR | I5: DR | J5: CR | K5: DR | L5: CR | M5: DR | N5: CR
A7: =+'Chart of Accounts'!A4 -> 101 | B7: =+'Chart of Accounts'!B4 -> Cash at Bank - ANZ | C7: ='Gen Ledger'!F7 -> 20057 | I7: =C7 -> 20057 | M7: =I7 -> 20057
A8: =+'Chart of Accounts'!A5 -> 110 | B8: =+'Chart of Accounts'!B5 -> Accounts Receivable | C8: ='Gen Ledger'!F16 -> 51202 | I8: =C8 -> 51202 | M8: =I8 -> 51202
A9: =+'Chart of Accounts'!A6 -> 112 | B9: =+'Chart of Accounts'!B6 -> Inventory | C9: ='Gen Ledger'!F27 -> 15320 | I9: =C9 -> 15320 | M9: =I9 -> 15320
A10: =+'Chart of Accounts'!A7 -> 115 | B10: =+'Chart of Accounts'!B7 -> Prepaid Insurance | C10: ='Gen Ledger'!F34 -> 1200 | H10: ='Gen Ledger'!E35 -> 100 | I10: =C10-H10 -> 1100 | M10: =I10 -> 1100
A11: =+'Chart of Accounts'!A8 -> 116 | B11: =+'Chart of Accounts'!B8 -> Prepaid Rent | C11: ='Gen Ledger'!F41 -> 15000 | H11: ='Gen Ledger'!E42 -> 5000 | I11: =C11-H11 -> 10000 | M11: =I11 -> 10000
A12: =+'Chart of Accounts'!A9 -> 118 | B12: =+'Chart of Accounts'!B9 -> Office Supplies | C12: ='Gen Ledger'!F49 -> 2220 | H12: ='Gen Ledger'!F206 -> 1850 | I12: =C12-H12 -> 370 | M12: =I12 -> 370
A13: =+'Chart of Accounts'!A10 -> 130 | B13: =+'Chart of Accounts'!B10 -> Store Equipment | C13: ='Gen Ledger'!F56 -> 29080 | I13: =C13 -> 29080 | M13: =I13 -> 29080
A14: =+'Chart of Accounts'!A11 -> 131 | B14: =+'Chart of Accounts'!B11 -> Accumulated Depreciation - Store Equipment | D14: ='Gen Ledger'!G62 -> 14040 | H14: ='Gen Ledger'!E63 -> 468 | J14: =D14+H14 -> 14508 | N14: =J14 -> 14508
A15: =+'Chart of Accounts'!A12 -> 135 | B15: =+'Chart of Accounts'!B12 -> Computer Equipment | C15: ='Gen Ledger'!F70 -> 25680 | I15: =C15 -> 25680 | M15: =I15 -> 25680
A16: =+'Chart of Accounts'!A13 -> 136 | B16: =+'Chart of Accounts'!B13 -> Accumulated Depreciation - Computer Equipment | D16: ='Gen Ledger'!G76 -> 15288 | H16: ='Gen Ledger'!E77 -> 570 | J16: =D16+H16 -> 15858 | N16: =J16 -> 15858
A17: =+'Chart of Accounts'!A14 -> 200 | B17: =+'Chart of Accounts'!B14 -> GST Clearing (Tax Payable GST) | D17: ='Gen Ledger'!G92 -> 2410 | J17: =D17 -> 2410 | N17: =J17 -> 2410
A18: =+'Chart of Accounts'!A15 -> 201 | B18: =+'Chart of Accounts'!B15 -> Accounts Payable | D18: ='Gen Ledger'!G101 -> 21886 | J18: =D18 -> 21886 | N18: =J18 -> 21886
A19: =+'Chart of Accounts'!A16 -> 203 | B19: =+'Chart of Accounts'!B16 -> Wages Payable | H19: ='Gen Ledger'!G107 -> 600 | J19: =H19 -> 600 | N19: =J19 -> 600
A20: =+'Chart of Accounts'!A17 -> 205 | B20: =+'Chart of Accounts'!B17 -> PAYG Tax Payable | D20: ='Gen Ledger'!G115 -> 1020 | J20: =D20 -> 1020 | N20: =J20 -> 1020
A21: =+'Chart of Accounts'!A18 -> 301 | B21: =+'Chart of Accounts'!B18 -> Capital | D21: ='Gen Ledger'!G123 -> 92500 | J21: =D21 -> 92500 | N21: =J21 -> 92500
A22: =+'Chart of Accounts'!A19 -> 302 | B22: =+'Chart of Accounts'!B19 -> Drawings | C22: ='Gen Ledger'!F131 -> 1000 | I22: =C22 -> 1000 | M22: =I22 -> 1000
A23: =+'Chart of Accounts'!A21 -> 401 | B23: =+'Chart of Accounts'!B21 -> Sales Revenue | D23: ='Gen Ledger'!G147 -> 38600 | J23: =D23 -> 38600 | L23: =J23 -> 38600
A24: =+'Chart of Accounts'!A22 -> 402 | B24: =+'Chart of Accounts'!B22 -> Sales Returns & Allowances | C24: ='Gen Ledger'!F154 -> 600 | I24: =C24 -> 600 | K24: =I24 -> 600
A25: =+'Chart of Accounts'!A23 -> 501 | B25: =+'Chart of Accounts'!B23 -> Cost of Sales | C25: ='Gen Ledger'!F164 -> 19000 | I25: =C25 -> 19000 | K25: =I25 -> 19000
A26: =+'Chart of Accounts'!A24 -> 503 | B26: =+'Chart of Accounts'!B24 -> Bank Charges | C26: ='Gen Ledger'!F171 -> 25 | I26: =C26 -> 25 | K26: =I26 -> 25
A27: =+'Chart of Accounts'!A25 -> 505 | B27: =+'Chart of Accounts'!B25 -> Depreciation Expense - Computer Equipment | F27: ='Gen Ledger'!F178 -> 570 | I27: =F27 -> 570 | K27: =I27 -> 570
A28: =+'Chart of Accounts'!A26 -> 506 | B28: =+'Chart of Accounts'!B26 -> Depreciation Expense - Store Equipment | F28: ='Gen Ledger'!F185 -> 468 | I28: =F28 -> 468 | K28: =I28 -> 468
A29: =+'Chart of Accounts'!A27 -> 510 | B29: =+'Chart of Accounts'!B27 -> Electrical Repairs Expense | C29: ='Gen Ledger'!F193 -> 430 | I29: =C29 -> 430 | K29: =I29 -> 430
A30: =+'Chart of Accounts'!A28 -> 520 | B30: =+'Chart of Accounts'!B28 -> Insurance Expense | F30: ='Gen Ledger'!F199 -> 100 | I30: =F30 -> 100 | K30: =I30 -> 100
A31: =+'Chart of Accounts'!A29 -> 542 | B31: =+'Chart of Accounts'!B29 -> Office Supplies Expense | F31: ='Gen Ledger'!F206 -> 1850 | I31: =F31 -> 1850 | K31: =I31 -> 1850
A32: =+'Chart of Accounts'!A30 -> 560 | B32: =+'Chart of Accounts'!B30 -> Rent Expense | F32: ='Gen Ledger'!F213 -> 5000 | I32: =F32 -> 5000 | K32: =I32 -> 5000
A33: =+'Chart of Accounts'!A31 -> 580 | B33: =+'Chart of Accounts'!B31 -> Telephone and Internet Expense | C33: ='Gen Ledger'!F220 -> 250 | I33: =C33 -> 250 | K33: =I33 -> 250
A34: =+'Chart of Accounts'!A32 -> 582 | B34: =+'Chart of Accounts'!B32 -> Utilities Expense | C34: ='Gen Ledger'!F227 -> 260 | I34: =C34 -> 260 | K34: =I34 -> 260
A35: =+'Chart of Accounts'!A33 -> 585 | B35: =+'Chart of Accounts'!B33 -> Wages Expense | C35: ='Gen Ledger'!F235 -> 4420 | F35: ='Gen Ledger'!D236 -> 600 | I35: =C35+F35 -> 5020 | K35: =I35 -> 5020
C36: =SUM(C6:C35) -> 185744 | D36: =SUM(D6:D35) -> 185744 | F36: =SUM(F7:F35) -> 8588 | H36: =SUM(H7:H35) -> 8588 | I36: =SUM(I7:I35) -> 187382 | J36: =SUM(J7:J35) -> 187382 | K36: =SUM(K7:K35) -> 33573 | L36: =SUM(L7:L35) -> 38600 | M36: =SUM(M7:M35) -> 153809 | N36: =SUM(N7:N35) -> 148782
B37: Net Profit | K37: =L36-K36 -> 5027 | N37: =K37 -> 5027
K38: =SUM(K36:K37) -> 38600 | L38: =SUM(L36:L37) -> 38600 | M38: =SUM(M36:M37) -> 153809 | N38: =SUM(N36:N37) -> 153809
A39: Proof-Unadjusted Trial Balance | C39: =C36-D36 -> 0
A40: Proof-Adjustments | C40: =+F36-H36 -> 0
A41: Proof-Adjusted Trial Balance | C41: =+I36-J36 -> 0
A42: Proof-Income Statement | C42: =+K38-L38 -> 0
A43: Proof-Balance Sheet | C43: =+M38-N38 -> 0

Sheet Income Sment & Chgs in Equity
B2: Classified Income Statement (see instructions)
B3: Month ended 30 April
A5: Revenue
B6: Sales Revenue | D6: =Worksheet!L23 -> 38600
B7: Less: Sales Returns & Allowances | C7: =Worksheet!K24 -> 600
B8: Net Sales Revenue | D8: =D6-C7 -> 38000
B9: Cost of Sales | C9: =Worksheet!K25 -> 19000
B10: Gross Profit | D10: =D8-C9 -> 19000
A12: Selling Expenses
B13: Wages Expense | C13: =Worksheet!K35 -> 5020
A14: Administrative Expenses
B15: Depreciation Expense - Computer Equipment | C15: =Worksheet!K27 -> 570
B16: Depreciation Expense - Store Equipment | C16: =Worksheet!K28 -> 468
B17: Electrical Repairs Expense | C17: =Worksheet!K29 -> 430
B18: Insurance Expense | C18: =Worksheet!K30 -> 100
B19: Office Supplies Expense | C19: =Worksheet!K31 -> 1850
B20: Rent Expense | C20: =Worksheet!K32 -> 5000
B21: Telephone and Internet Expense | C21: =Worksheet!K33 -> 250
B22: Utilities Expense | C22: =Worksheet!K34 -> 260
A23: Finance Expenses
B24: Bank Charges | C24: =Worksheet!K26 -> 25
B25: Total Expenses | D25: =SUM(C13:C24) -> 13973
A27: Profit | D27: =D10-D25 -> 5027
B40: Statement of Changes in Equity
B41: Month Ended 30 April
A44: A. Miles, Capital, 1 April | D44: ='Gen Ledger'!G122 -> 90000
B45: Add: Capital | C45: ='Gen Ledger'!E123 -> 2500
B46: Add: Profit | C46: =D27 -> 5027 | D46: =D44+C45+C46 -> 97527
B48: Less: Drawings | D48: =Worksheet!I22 -> 1000
A49: A. Miles, Capital, 30 April | D49: =D46-D48 -> 96527

Sheet Balance Sheet
A2: Classified Comparative Balance Sheet as at 30 April
C3: 30 April compared to 31 March
B5: ASSETS | F5: 44315 | H5: 44285
B7: Current Assets
B8: Cash at Bank - ANZ | F8: =Worksheet!M7 -> 20057 | H8: ='Chart of Accounts'!C4 -> 14870
B9: Accounts Receivable | F9: =Worksheet!M8 -> 51202 | H9: ='Chart of Accounts'!C5 -> 56518
B10: Inventory | F10: =Worksheet!M9 -> 15320 | H10: ='Chart of Accounts'!C6 -> 24480
B11: Prepaid Insurance | F11: =Worksheet!M10 -> 1100 | H11: 0
B12: Prepaid Rent | F12: =Worksheet!M11 -> 10000 | H12: ='Chart of Accounts'!C8 -> 15000
B13: =+'Chart of Accounts'!B9 -> Office Supplies | F13: =Worksheet!M12 -> 370 | H13: ='Chart of Accounts'!C9 -> 1520
B14: Total Current Assets | F14: =SUM(F8:F13) -> 98049 | H14: =SUM(H8:H13) -> 112388
B16: Non-Current Assets
B17: Store Equipment | F17: =Worksheet!M13 -> 29080 | H17: ='Chart of Accounts'!C10 -> 29080
B18: Less: Accumulated Depreciation - Store Equipment | F18: =Worksheet!N14 -> 14508 | H18: ='Chart of Accounts'!D11 -> 14040
B19: Computer Equipment | F19: =Worksheet!M15 -> 25680 | H19: ='Chart of Accounts'!C12 -> 24460
B20: Less: Accumulated Depreciation - Computer Equipment | F20: =Worksheet!N16 -> 15858 | H20: ='Chart of Accounts'!D13 -> 15288
B21: Total Non-Current Assets | F21: =F17-F18+F19-F20 -> 24394 | H21: =H17-H18+H19-H20 -> 24212
B22: TOTAL ASSETS | F22: =F14+F21 -> 122443 | H22: =H14+H21 -> 136600
B24: LIABILITIES AND EQUITY
B26: Liabilities
B27: GST Clearing (Tax Payable GST) | F27: =Worksheet!N17 -> 2410 | H27: ='Chart of Accounts'!D14 -> 12450
B28: Accounts Payable | F28: =Worksheet!N18 -> 21886 | H28: ='Chart of Accounts'!D15 -> 28970
B29: Wages Payable | F29: =Worksheet!N19 -> 600 | H29: 0
B30: PAYG Tax Payable | F30: =Worksheet!N20 -> 1020 | H30: ='Chart of Accounts'!D17 -> 5180
B31: Total Liabilities | F31: =SUM(F27:F30) -> 25916 | H31: =SUM(H27:H30) -> 46600
B33: Equity
B34: Capital | F34: =Worksheet!N21 -> 92500 | H34: ='Chart of Accounts'!D18 -> 90000
B35: Less: Drawings | F35: =Worksheet!M22 -> 1000 | H35: 0
B36: Net Profit | F36: =Worksheet!N37 -> 5027 | H36: 0
B37: Total Equity | F37: =F34-F35+F36 -> 96527 | H37: =SUM(H34:H36) -> 90000
B38: TOTAL LIABILITIES AND EQUITY | F38: =F31+F37 -> 122443 | H38: =H31+H37 -> 136600

Sheet Post Cl Trial Bal
A1: Post Closing Trial Balance
A2: as at 30 April
A3: (After the closing journal entries are posted into the general ledger)
B4: Debit | C4: Credit
A5: Cash at Bank - ANZ | B5: ='Gen Ledger'!F7 -> 20057
A6: Accounts Receivable | B6: ='Gen Ledger'!F16 -> 51202
A7: Inventory | B7: ='Gen Ledger'!F27 -> 15320
A8: Prepaid Insurance | B8: ='Gen Ledger'!F35 -> 1100
A9: Prepaid Rent | B9: ='Gen Ledger'!F42 -> 10000
A10: Office Supplies | B10: ='Gen Ledger'!F50 -> 370
A11: Store Equipment | B11: ='Gen Ledger'!F56 -> 29080
A12: Accumulated Depreciation - Store Equipment | C12: ='Gen Ledger'!G63 -> 14508
A13: Computer Equipment | B13: ='Gen Ledger'!F70 -> 25680
A14: Accumulated Depreciation - Computer Equipment | C14: ='Gen Ledger'!G77 -> 15858
A15: GST Clearing (Tax Payable GST) | C15: ='Gen Ledger'!G92 -> 2410
A16: Accounts Payable | C16: ='Gen Ledger'!G101 -> 21886
A17: Wages Payable | C17: ='Gen Ledger'!G107 -> 600
A18: PAYG Tax Payable | C18: ='Gen Ledger'!G115 -> 1020
A19: Capital | C19: ='Gen Ledger'!G125 -> 96527
B20: =SUM(B5:B19) -> 152809 | C20: =SUM(C5:C19) -> 152809
